LICENSE.txt
MANIFEST.in
README.md
setup.cfg
setup.py
debian/changelog
src/lot/__init__.py
src/lot.egg-info/PKG-INFO
src/lot.egg-info/SOURCES.txt
src/lot.egg-info/dependency_links.txt
src/lot.egg-info/top_level.txt
wrap/lot.i