Metadata-Version: 2.1
Name: lot
Version: 0.2.1
Summary: A module to control SBC GPIO
Home-page: https://github.com/loliot
Author: Hyeonki Hong
Author-email: hhk7734@gmail.com
License: MIT
Project-URL: Source, https://github.com/loliot/python3-lot.git
Keywords: lot,GPIO
Platform: UNKNOWN
Classifier: Programming Language :: Python :: 3
Classifier: License :: OSI Approved :: MIT License
Classifier: Operating System :: POSIX :: Linux
Classifier: Intended Audience :: Developers
Classifier: Topic :: Software Development
Classifier: Topic :: System :: Hardware
